niwrap_helper/__init__.py
niwrap_helper/bids.py
niwrap_helper/styx.py
niwrap_helper/types.py
niwrap_helper-0.6.1.dist-info/METADATA
niwrap_helper-0.6.1.dist-info/WHEEL
niwrap_helper-0.6.1.dist-info/RECORD
